setup.py
phasepersist/__init__.py
phasepersist/phasepersist.py
phasepersist.egg-info/PKG-INFO
phasepersist.egg-info/SOURCES.txt
phasepersist.egg-info/dependency_links.txt
phasepersist.egg-info/not-zip-safe
phasepersist.egg-info/top_level.txt