Metadata-Version: 1.0
Name: phasepersist
Version: 0.1
Summary: Load and save python stuff in pickle files.
Home-page: http://github.com/phasemix/phasepersist
Author: Roberto Allende
Author-email: rallende@gmail.com
License: Apache 2.0
Platform: UNKNOWN
